influ/__init__.py
influ/finder/__init__.py
influ/finder/influence.py
influ/finder/model.py
influ/reader/__init__.py
influ/reader/datasets.yaml
influ/reader/direct.py
influ/reader/konect.py
influ/reader/merge.py
influ-0.3.0.dist-info/LICENSE.txt
influ-0.3.0.dist-info/METADATA
influ-0.3.0.dist-info/WHEEL
influ-0.3.0.dist-info/top_level.txt
influ-0.3.0.dist-info/RECORD
