Metadata-Version: 2.1
Name: influ
Version: 0.3.0
Summary: Who influences whom in social network - an application for finding key nodes
Home-page: https://gitlab.com/chgrzegorz/dyplom-code
Author: Grzegorz Chilczuk
Author-email: chgrzegorz@pm.me
License: GPLv2
Project-URL: Documentation, https://influ.readthedocs.io
Keywords: graph social network influence
Platform: UNKNOWN
Classifier: Development Status :: 3 - Alpha
Classifier: License :: OSI Approved :: GNU General Public License v2 (GPLv2)
Classifier: Programming Language :: Python :: 3.6
Classifier: Programming Language :: Python :: 3.7
Requires-Dist: python-igraph (<1.0.0,>=0.7.1.post6)
Requires-Dist: numpy (<2.0.0,>=1.15.2)
Requires-Dist: pandas (<1.0.0,>=0.23.4)
Requires-Dist: PyYAML (<4.0.0,>=3.13.0)
Requires-Dist: requests (<3.0.0,>=2.20.1)
Requires-Dist: matplotlib (<4.0.0,>=3.0.0)
Requires-Dist: pycairo (<2.0.0,>=1.17.1)
